cuesplitter/__init__.py
cuesplitter/cli.py
cuesplitter/core.py
cuesplitter/ffmpeg.py
cuesplitter/models/__init__.py
cuesplitter/models/album.py
cuesplitter/tags.py
cuesplitter-0.1.1.dist-info/METADATA
cuesplitter-0.1.1.dist-info/WHEEL
cuesplitter-0.1.1.dist-info/entry_points.txt
cuesplitter-0.1.1.dist-info/licenses/LICENSE
cuesplitter-0.1.1.dist-info/RECORD
