Metadata-Version: 2.4
Name: cuesplitter
Version: 0.1.1
Summary: Lossless, bit-perfect splitting of FLAC albums using CUE sheets. PCM verification and automatic tagging.
License: MIT
License-File: LICENSE
Keywords: ffmpeg,tags,split,verification,joiner,flac,join,ffmpeg-wrapper,splitter,bit-perfect
Author: Olezhich
Requires-Python: >=3.12
Classifier: License :: OSI Approved :: MIT License
Classifier: Programming Language :: Python :: 3
Classifier: Programming Language :: Python :: 3.12
Classifier: Programming Language :: Python :: 3.13
Classifier: Programming Language :: Python :: 3.14
Requires-Dist: cuetools (>=1.0.1,<2.0.0)
Requires-Dist: mutagen (>=1.47.0,<2.0.0)
Requires-Dist: typer (>=0.20.1,<0.21.0)
Project-URL: Changelog, https://github.com/Olezhich/CueSplitter/blob/main/CHANGELOG.md
Project-URL: Homepage, https://github.com/Olezhich/CueSplitter
Project-URL: Repository, https://github.com/Olezhich/CueSplitter
